mandown/__init__.py
mandown/api.py
mandown/base.py
mandown/cli.py
mandown/comic.py
mandown/convert_utils.py
mandown/errors.py
mandown/io.py
mandown/processor/__init__.py
mandown/processor/ops.py
mandown/processor/profiles.py
mandown/request_utils.py
mandown/sources/__init__.py
mandown/sources/base_source.py
mandown/sources/common_source.py
mandown/sources/source_batoto.py
mandown/sources/source_kuaikanmanhua.py
mandown/sources/source_mangadex.py
mandown/sources/source_manganato.py
mandown/sources/source_readcomiconline.py
mandown/sources/source_thecomicseries.py
mandown/sources/source_webtoons.py
mandown/ui/form.ui
mandown/ui/mainwin.py
mandown/ui/mandown-qt.pyproject
mandown/ui/ui.py
mandown-1.12.1.dist-info/LICENSE
mandown-1.12.1.dist-info/METADATA
mandown-1.12.1.dist-info/WHEEL
mandown-1.12.1.dist-info/entry_points.txt
mandown-1.12.1.dist-info/RECORD
