Metadata-Version: 2.3
Name: mandown
Version: 1.12.1
Summary: Comic/manga/webtoon downloader and CBZ/EPUB/MOBI/PDF converter
License: AGPL-3.0-only
Keywords: manga,comic,downloader,download,webtoons,webtoon
Author: potatoeggy
Author-email: eggyrules@gmail.com
Requires-Python: >=3.10,<3.14
Classifier: License :: OSI Approved :: GNU Affero General Public License v3
Classifier: Programming Language :: Python :: 3
Classifier: Programming Language :: Python :: 3.10
Classifier: Programming Language :: Python :: 3.11
Classifier: Programming Language :: Python :: 3.12
Classifier: Programming Language :: Python :: 3.13
Provides-Extra: gui
Requires-Dist: PySide6 (>=6.8.1.1,<7.0.0.0) ; extra == "gui"
Requires-Dist: beautifulsoup4 (>=4.13.4,<5.0.0)
Requires-Dist: comicon (>=1.5.0,<2.0.0)
Requires-Dist: feedparser (>=6.0.11,<7.0.0)
Requires-Dist: filetype (>=1.2.0,<2.0.0)
Requires-Dist: lxml (>=5.4.0,<6.0.0)
Requires-Dist: natsort (>=8.4.0,<9.0.0)
Requires-Dist: pillow (>=11.2.1,<12.0.0)
Requires-Dist: python-slugify (>=8.0.4,<9.0.0)
Requires-Dist: requests (>=2.32.3,<3.0.0)
Requires-Dist: typer-slim (>=0.15.3,<0.16.0)
Project-URL: Documentation, https://github.com/potatoeggy/mandown
Project-URL: Repository, https://github.com/potatoeggy/mandown
